<?xml version="1.0" encoding="utf-8"?>
<openerp>
    <data>
        <record id="view_order_form_change_due_date" model="ir.ui.view">
            <field name="model">sale.order</field>
            <field name="inherit_id" ref="sale.view_order_form"/>
            <field name="arch" type="xml">
                <data>
                    <xpath expr="//field[@name='client_order_ref']" position="after">
                       <field name="date_value"/>
                    </xpath>
                </data>
            </field>
        </record>
    </data>
</openerp>
